<?xml version = '1.0' encoding = 'UTF-8'?>
<relationalModel class="oracle.dbtools.crest.model.design.relational.RelationalDesign" name="Relational_1" id="DA2B8B81-53B5-7260-DC06-1F923720FFE2" mainViewID="19B09103-1965-692D-3661-77EE6A02C510">
<createdBy>labsfiap</createdBy>
<createdTime>2025-11-12 11:17:54 UTC</createdTime>
<ownerDesignName>Database_Modeler</ownerDesignName>
<shouldBeOpen>false</shouldBeOpen>
<selectedRDBMSSite>32076570-2523-435C-2E92-BF29817DFF70</selectedRDBMSSite>
</relationalModel>